traps/__init__.py
traps/__main__.py
traps/cli.py
traps/downloader.py
traps/utils.py
traps-3.0.2.dist-info/LICENSE
traps-3.0.2.dist-info/METADATA
traps-3.0.2.dist-info/WHEEL
traps-3.0.2.dist-info/entry_points.txt
traps-3.0.2.dist-info/RECORD
