Metadata-Version: 2.1
Name: traps
Version: 3.0.2
Summary: How about you pip install some traps?
License: MIT
Keywords: anime,traps,python,package,library,lib,module,cli
Author: Rdimo
Author-email: contact.rdimo@gmail.com
Requires-Python: >=3.7,<4.0
Classifier: Intended Audience :: Developers
Classifier: Intended Audience :: Other Audience
Classifier: License :: OSI Approved :: MIT License
Classifier: Natural Language :: English
Classifier: Operating System :: OS Independent
Classifier: Programming Language :: Python :: 3
Classifier: Programming Language :: Python :: 3.7
Classifier: Programming Language :: Python :: 3.8
Classifier: Programming Language :: Python :: 3.9
Classifier: Programming Language :: Python :: 3.10
Classifier: Programming Language :: Python :: 3.11
Classifier: Programming Language :: Python :: 3.12
Requires-Dist: click (>=8.1.3,<8.2.0)
Requires-Dist: loguru (>=0.6.0,<0.7.0)
Requires-Dist: requests (>=2.28.0,<3.0.0)
Project-URL: Bug Tracker, https://github.com/ag02-org/pip-install-traps/issues
Project-URL: Homeage, https://github.com/ag02-org/pip-install-traps
